MAC_unit.sv
`timescale 1ns / 1ns

module MAC_unit#(
    parameter A_Input_Width = 16,   // Width of input A and weight B
    parameter C_Output_Width = 32   // Width of output C (Accumulated result)
)(
    input logic clk,
    input logic reset,
    input logic enable,
    input logic signed [A_Input_Width-1:0] A_in,
    input logic signed [A_Input_Width-1:0] B_in,
    input logic signed [C_Output_Width-1:0] C_in,
    output logic signed [A_Input_Width-1:0] A_out,
    // output logic signed [A_Input_Width-1:0] B_out,
    output logic signed [C_Output_Width-1:0] C_out
);



localparam Prod_Width = A_Input_Width*2; // Width after multiplication
logic signed [Prod_Width-1:0] Product;
logic signed [C_Output_Width-1:0] Acc_reg; //Internal reg

// assign Product = A_in * B_in; // Signed multiplication
// assign Acc_reg = C_in + $signed(Product); // Output the accumulated result

always_ff @(posedge clk) begin
    if (reset)
    begin
    A_out <= 0;
    C_out <= 0;
    end

    else begin
    if (enable) begin
        C_out <= A_in * B_in; // Output the accumulated result
        A_out <= A_in;
    end
    else begin
        C_out <= C_out; 
        A_out <= A_out;
        // B_out <= B_out;
    end

    
    end
end
// assign C_out = Acc_reg;
endmodule

Systolic_Array.sv
module Systolic_Array #(
    parameter N=2,
    parameter A_Input_Width =16,
    parameter C_Output_Width =32)(
    input logic clk,
    input logic reset,
    input logic start,
    input logic enable,
    input logic preload, // Signal to indicate the preloading phase of weights (B inputs) fow weight-stationary dataflow
    input logic signed [A_Input_Width-1:0] A_in [N][N],
    input logic signed [A_Input_Width-1:0] B_in [N][N],
    output logic signed [C_Output_Width-1:0] C_out[N][N],
    output logic done
    );

    localparam N_Elements = N*N;
    logic signed [A_Input_Width-1:0] A_bus[0:N-1][0:N]; // Extra column for input coming in from left
    logic signed [A_Input_Width-1:0] B_bus[0:N-1][0:N-1]; // Bus to store B weights, stationary in this dataflow. No extra row/column needed.
    logic signed [C_Output_Width-1:0] C_bus[0:N][0:N-1]; // Accumulation matrix for each MAC unit
    logic signed [C_Output_Width-1:0] C_acc[0:N][0:N-1]; // new register to hold the accumulated value for each MAC unit
    // logic signed [N_Elements-1:0][A_Input_Width-1:0] B_in_staggered = B_in;
    // logic signed [A_Input_Width-1:0] B_in_staggered[N][N];
    // assign B_in_staggered = B_in; // Direct assignment for now

    logic enable_bus[0:N-1][0:N-1]; // Enable signals for clock-gating each MAC unit
    integer i, j;
    int row_i, col_j;
    int clkcount; // Counter to track the number of clock cycles and the progress of computation
    logic running; // Signal to indicate the start of computation

    logic signed [C_Output_Width-1:0] C_bottom[0:N-1];
    int collection_phase; // Track the phase of output collection within the collection window
    always_comb begin 
        for (j = 0; j < N; j = j + 1) begin
            C_bottom[j] = C_acc[2][j]; // Output the accumulated results from the first row of C_acc to C_out, can be done in the same cycle as the accumulation since it's just a register transfer
        end
        
    end

    always_ff @(posedge clk or posedge reset) begin
        if (reset) begin
            clkcount <= '0; // Reset clock counter, running and done signals
            running <= 1'b0;
            done <= 1'b0;
        end

        else begin 
            done <= 1'b0;

            if (preload && !running) begin
                for (row_i = 0; row_i < N; row_i = row_i + 1) begin
                    for (col_j = 0; col_j < N; col_j = col_j + 1) begin
                        B_bus[row_i][col_j] <= B_in[row_i][col_j]; //Preload the weights (B inputs) into the array before starting the computation
                    end
                end
            end

            if (start&&!running) begin // Start signal received
                running <= 1'b1;
                clkcount <= '0;
            end
        
            else if (running) begin
                clkcount <= clkcount + 1;

                if (clkcount >= N*2+1) begin // Computation is complete after N*2 cycles
                    running <= 1'b0;
                    done <= 1'b1;
                end

                // for (col_j = 0; col_j < N; col_j = col_j + 1) begin
                    
                    for (row_i = 0; row_i < N+1; row_i = row_i + 1) begin
                        for (col_j = 0; col_j < N; col_j = col_j + 1) begin
                            
                            if (clkcount >= col_j && clkcount < row_i + col_j + N) begin
                                enable_bus[row_i][col_j] <= 1'b1; // Enable the first column of MAC units in a staggered manner based on clock count
                            end

                            else begin
                                enable_bus[row_i][col_j] <= 1'b0;
                            end
                        end
                            
                        
                        
                        if (clkcount>= 0 && clkcount <  N) begin
                            // for (row_i = 0; row_i < N; row_i = row_i + 1) begin
                            //     A_bus[row_i][0] <= A_in[clkcount-row_i][row_i]; // Load input A values into first column during start and subsequent cycles
                            // end
                            A_bus[row_i][0] <= A_in[clkcount][row_i]; // Load input A values into first column during start and subsequent cycles
                        end
                        else begin
                            A_bus[row_i][0] <= '0; // Zero input if already running and MAC is enabled
                        end
                    end

                    
                    if (clkcount <= 3*N) begin

                            for (row_i = 0; row_i < N + 1; row_i = row_i + 1) begin
                                for (col_j = 0; col_j < N; col_j = col_j + 1) begin
                                    // C_acc[row_i][col_j] <= C_bus[row_i][col_j] + C_acc[row_i-1][col_j];
                                    C_acc[row_i][col_j] <= C_bus[row_i][col_j] + C_bus[row_i - 1][col_j]; // Accumulate the results from the MAC units in a separate register, can be done in the same cycle as the MAC computation since it's just an addition, and will be used for the next cycle's accumulation. This is to ensure we capture the intermediate results correctly without overwriting them in C_bus which is directly connected to the MAC outputs.
                                end
                            end

                            // if (clkcount >= N && clkcount < 3*N) begin
                                for (col_j = 0; col_j < N; col_j = col_j + 1) begin
                                    if (collection_phase>=col_j && collection_phase < col_j + N) begin
                                        C_out[collection_phase-col_j][col_j] <= C_acc[2][col_j]; // Output the accumulated results from the accumulation row of C_acc to C_out, can be done in the same cycle as the accumulation since it's just a register transfer
                                        // collection_phase <= clkcount - (col_j + N); // Set the collection phase based on the clock count and column index to track which row of results is being output
                                    end
                                    // C_out[clkcount - col_j][col_j] <= C_acc[2][col_j]; // Output the accumulated results from the accumulation row of C_acc to C_out, can be done in the same cycle as the accumulation since it's just a register transfer
                                end
                                if (clkcount > N && clkcount < 3*N) begin
                                collection_phase <= collection_phase + 1; // Increment the collection phase count to for the next row of results in the next cycle
                                end
                            // end
                    end
                    else begin
                            // C_acc[2][1] <= 'd0;
                    end
                        
                    
                // end

            end   
        end
        
    end

            genvar r, c;
            generate

                for (r = 0; r < N; r = r + 1) begin : row_loop
                    for (c = 0; c < N; c = c + 1) begin : col_loop
                        logic signed [A_Input_Width-1:0] A_in_wire, B_in_wire;
                        logic signed [A_Input_Width-1:0] A_out_wire, B_out_wire;
                        logic signed [C_Output_Width-1:0] C_out_wire;
                        // localparam logic [$clog2(N*2+4)-1:0] row = r;
                        // localparam logic [$clog2(N*2+4)-1:0] col = c;

                        assign enable_bus[r][c] = enable;   // Clock-gate each MAC unit based on the global enable signal

                        MAC_unit #(
                            .A_Input_Width(A_Input_Width),
                            .C_Output_Width(C_Output_Width)
                        )

                        mac_inst(
                            .clk(clk),
                            .reset(reset),
                            .enable(enable_bus[r][c]),
                            .A_in(A_bus[r][c]), // Load from corresponding input and weight buses
                            .B_in(B_bus[r][c]),
                            .C_in(C_bus[r+1][c]),
                            .A_out(A_bus[r][c+1]), // Forward A output to the right
                            // .B_out(B_bus[r+1][c]), // Forward B output downward
                            .C_out(C_bus[r+1][c])
                        );       
                    end
                end
            endgenerate


endmodule

tb_systolicarray_2x2.sv
`timescale 1ns/1ns

module tb_systolicarray_2x2;

localparam N = 2;
localparam A_Input_Width = 16;
localparam C_Output_Width = 32;
localparam N_Elements = N*N;

logic clk;
logic reset;
logic enable;
logic start;
logic preload;
wire done;
logic [A_Input_Width-1:0] A_in [N][N];  
logic [A_Input_Width-1:0] B_in [N][N];
wire [C_Output_Width-1:0] C_out[N][N];

    // Instantiate DUT
    Systolic_Array dut (
        .clk(clk),
        .reset(reset),
        .enable(enable),
        .A_in(A_in),
        .B_in(B_in),
        .C_out(C_out),
        .start(start),
        .preload(preload),
        .done(done)

    );

    // Clock generation
    always #5 clk = ~clk; // 10ns period, 100MHz

    integer i, j;

    initial begin
        $display("---- Systolic Array 2x2 Testbench Start ----");
        
        $dumpfile("tb_systolicarray_2x2.vcd");
        $dumpvars(0, tb_systolicarray_2x2);
        clk = 0;
        reset = 0;
        preload = 1;
        #10;
        start = 1;
        // enable = 1'b1;

        // Example matrices:
        // A = [1 2; 3 4]
        // B = [5 6; 7 8]
        A_in[0][0] = 'd1; A_in[0][1] = 'd2;
        A_in[1][0] = 'd3; A_in[1][1] = 'd4;
        // A_in[0] = 'd1; A_in[1] = 'd2;
        // A_in[2] = 'd3; A_in[3] = 'd4;
        // B_in = '{
        // '{16'd5, 16'd6},     // row 0
        // '{16'd7, 16'd8}      // row 1
        // };
        B_in[0][0] = 'd5; B_in[0][1] = 'd6;      //why isn't this working??!!
        B_in[1][0] = 'd7;                        // weird...it works after commenting above assignments
        B_in[1][1] = 'd8;
        // B_in[0] = 'd5; B_in[1] = 'd6;
        // B_in[2] = 'd7; B_in[3] = 'd8;
        // Reset pulse
        // #5;
        // reset = 0;

        //  enable = 1;
        // @(posedge clk);
        // start = 1;
        #10;
        @(posedge clk);
        start = 0;
        preload = 0; // Clear preload after starting the computation

        // Wait enough cycles for systolic pipeline
        //  #150;
        $display("reset= %d, start= %d, done= %d, running= %d, clkcount= %d", reset, start, done, dut.running, dut.clkcount);
        wait (done == 1);

        $display("Computed Matrix C:");
        for (i = 0; i < 2; i = i + 1) begin
            for (j = 0; j < 2; j = j + 1) begin
                $display("C[%0d][%0d] = %0d", i, j, C_out[i][j]);
            end
        end

        // Expected result:
        // [1*5 + 2*7, 1*6 + 2*8] = [19, 22]
        // [3*5 + 4*7, 3*6 + 4*8] = [43, 50]

        $display("Expected:");
        $display("C = [19 22; 43 50]");
        #10;

        $display("---- Test Completed ----");
        $finish;
    end

endmodule

obj_dir/tb_systolicarray_2x2.vcd
$version Generated by VerilatedVcd $end
$timescale 1ns $end
 $scope module tb_systolicarray_2x2 $end
  $var wire 32 { N [31:0] $end
  $var wire 32 | A_Input_Width [31:0] $end
  $var wire 32 } C_Output_Width [31:0] $end
  $var wire 32 ~ N_Elements [31:0] $end
  $var wire 1 z clk $end
  $var wire 1 # reset $end
  $var wire 1 !! enable $end
  $var wire 1 $ start $end
  $var wire 1 % preload $end
  $var wire 1 J done $end
  $var wire 16 & A_in[0][0] [15:0] $end
  $var wire 16 ' A_in[0][1] [15:0] $end
  $var wire 16 ( A_in[1][0] [15:0] $end
  $var wire 16 ) A_in[1][1] [15:0] $end
  $var wire 16 * B_in[0][0] [15:0] $end
  $var wire 16 + B_in[0][1] [15:0] $end
  $var wire 16 , B_in[1][0] [15:0] $end
  $var wire 16 - B_in[1][1] [15:0] $end
  $var wire 32 K C_out[0][0] [31:0] $end
  $var wire 32 L C_out[0][1] [31:0] $end
  $var wire 32 M C_out[1][0] [31:0] $end
  $var wire 32 N C_out[1][1] [31:0] $end
  $var wire 32 . i [31:0] $end
  $var wire 32 / j [31:0] $end
  $scope module dut $end
   $var wire 32 { N [31:0] $end
   $var wire 32 | A_Input_Width [31:0] $end
   $var wire 32 } C_Output_Width [31:0] $end
   $var wire 1 z clk $end
   $var wire 1 # reset $end
   $var wire 1 $ start $end
   $var wire 1 !! enable $end
   $var wire 1 % preload $end
   $var wire 16 0 A_in[0][0] [15:0] $end
   $var wire 16 1 A_in[0][1] [15:0] $end
   $var wire 16 2 A_in[1][0] [15:0] $end
   $var wire 16 3 A_in[1][1] [15:0] $end
   $var wire 16 4 B_in[0][0] [15:0] $end
   $var wire 16 5 B_in[0][1] [15:0] $end
   $var wire 16 6 B_in[1][0] [15:0] $end
   $var wire 16 7 B_in[1][1] [15:0] $end
   $var wire 32 O C_out[0][0] [31:0] $end
   $var wire 32 P C_out[0][1] [31:0] $end
   $var wire 32 Q C_out[1][0] [31:0] $end
   $var wire 32 R C_out[1][1] [31:0] $end
   $var wire 1 J done $end
   $var wire 32 ~ N_Elements [31:0] $end
   $var wire 16 @ A_bus[0][0] [15:0] $end
   $var wire 16 A A_bus[0][1] [15:0] $end
   $var wire 16 B A_bus[0][2] [15:0] $end
   $var wire 16 C A_bus[1][0] [15:0] $end
   $var wire 16 D A_bus[1][1] [15:0] $end
   $var wire 16 E A_bus[1][2] [15:0] $end
   $var wire 16 S B_bus[0][0] [15:0] $end
   $var wire 16 T B_bus[0][1] [15:0] $end
   $var wire 16 U B_bus[1][0] [15:0] $end
   $var wire 16 V B_bus[1][1] [15:0] $end
   $var wire 32 p C_bus[0][0] [31:0] $end
   $var wire 32 q C_bus[0][1] [31:0] $end
   $var wire 32 r C_bus[1][0] [31:0] $end
   $var wire 32 s C_bus[1][1] [31:0] $end
   $var wire 32 t C_bus[2][0] [31:0] $end
   $var wire 32 u C_bus[2][1] [31:0] $end
   $var wire 32 W C_acc[0][0] [31:0] $end
   $var wire 32 X C_acc[0][1] [31:0] $end
   $var wire 32 Y C_acc[1][0] [31:0] $end
   $var wire 32 Z C_acc[1][1] [31:0] $end
   $var wire 32 [ C_acc[2][0] [31:0] $end
   $var wire 32 \ C_acc[2][1] [31:0] $end
   $var wire 1 ] enable_bus[0][0] $end
   $var wire 1 ^ enable_bus[0][1] $end
   $var wire 1 _ enable_bus[1][0] $end
   $var wire 1 ` enable_bus[1][1] $end
   $var wire 32 "! i [31:0] $end
   $var wire 32 #! j [31:0] $end
   $var wire 32 a row_i [31:0] $end
   $var wire 32 b col_j [31:0] $end
   $var wire 32 c clkcount [31:0] $end
   $var wire 1 d running $end
   $var wire 32 e C_bottom[0] [31:0] $end
   $var wire 32 f C_bottom[1] [31:0] $end
   $var wire 32 g collection_phase [31:0] $end
   $scope module row_loop[0] $end
    $scope module col_loop[0] $end
     $var wire 16 $! A_in_wire [15:0] $end
     $var wire 16 %! B_in_wire [15:0] $end
     $var wire 16 &! A_out_wire [15:0] $end
     $var wire 16 '! B_out_wire [15:0] $end
     $var wire 32 (! C_out_wire [31:0] $end
     $scope module mac_inst $end
      $var wire 32 | A_Input_Width [31:0] $end
      $var wire 32 } C_Output_Width [31:0] $end
      $var wire 1 z clk $end
      $var wire 1 # reset $end
      $var wire 1 h enable $end
      $var wire 16 F A_in [15:0] $end
      $var wire 16 i B_in [15:0] $end
      $var wire 32 v C_in [31:0] $end
      $var wire 16 8 A_out [15:0] $end
      $var wire 32 9 C_out [31:0] $end
      $var wire 32 } Prod_Width [31:0] $end
      $var wire 32 )! Product [31:0] $end
      $var wire 32 *! Acc_reg [31:0] $end
     $upscope $end
    $upscope $end
    $scope module col_loop[1] $end
     $var wire 16 +! A_in_wire [15:0] $end
     $var wire 16 ,! B_in_wire [15:0] $end
     $var wire 16 -! A_out_wire [15:0] $end
     $var wire 16 .! B_out_wire [15:0] $end
     $var wire 32 /! C_out_wire [31:0] $end
     $scope module mac_inst $end
      $var wire 32 | A_Input_Width [31:0] $end
      $var wire 32 } C_Output_Width [31:0] $end
      $var wire 1 z clk $end
      $var wire 1 # reset $end
      $var wire 1 j enable $end
      $var wire 16 G A_in [15:0] $end
      $var wire 16 k B_in [15:0] $end
      $var wire 32 w C_in [31:0] $end
      $var wire 16 : A_out [15:0] $end
      $var wire 32 ; C_out [31:0] $end
      $var wire 32 } Prod_Width [31:0] $end
      $var wire 32 0! Product [31:0] $end
      $var wire 32 1! Acc_reg [31:0] $end
     $upscope $end
    $upscope $end
   $upscope $end
   $scope module row_loop[1] $end
    $scope module col_loop[0] $end
     $var wire 16 2! A_in_wire [15:0] $end
     $var wire 16 3! B_in_wire [15:0] $end
     $var wire 16 4! A_out_wire [15:0] $end
     $var wire 16 5! B_out_wire [15:0] $end
     $var wire 32 6! C_out_wire [31:0] $end
     $scope module mac_inst $end
      $var wire 32 | A_Input_Width [31:0] $end
      $var wire 32 } C_Output_Width [31:0] $end
      $var wire 1 z clk $end
      $var wire 1 # reset $end
      $var wire 1 l enable $end
      $var wire 16 H A_in [15:0] $end
      $var wire 16 m B_in [15:0] $end
      $var wire 32 x C_in [31:0] $end
      $var wire 16 < A_out [15:0] $end
      $var wire 32 = C_out [31:0] $end
      $var wire 32 } Prod_Width [31:0] $end
      $var wire 32 7! Product [31:0] $end
      $var wire 32 8! Acc_reg [31:0] $end
     $upscope $end
    $upscope $end
    $scope module col_loop[1] $end
     $var wire 16 9! A_in_wire [15:0] $end
     $var wire 16 :! B_in_wire [15:0] $end
     $var wire 16 ;! A_out_wire [15:0] $end
     $var wire 16 <! B_out_wire [15:0] $end
     $var wire 32 =! C_out_wire [31:0] $end
     $scope module mac_inst $end
      $var wire 32 | A_Input_Width [31:0] $end
      $var wire 32 } C_Output_Width [31:0] $end
      $var wire 1 z clk $end
      $var wire 1 # reset $end
      $var wire 1 n enable $end
      $var wire 16 I A_in [15:0] $end
      $var wire 16 o B_in [15:0] $end
      $var wire 32 y C_in [31:0] $end
      $var wire 16 > A_out [15:0] $end
      $var wire 32 ? C_out [31:0] $end
      $var wire 32 } Prod_Width [31:0] $end
      $var wire 32 >! Product [31:0] $end
      $var wire 32 ?! Acc_reg [31:0] $end
     $upscope $end
    $upscope $end
   $upscope $end
  $upscope $end
 $upscope $end
$enddefinitions $end


#0
0#
0$
1%
b0000000000000000 &
b0000000000000000 '
b0000000000000000 (
b0000000000000000 )
b0000000000000000 *
b0000000000000000 +
b0000000000000000 ,
b0000000000000000 -
b00000000000000000000000000000000 .
b00000000000000000000000000000000 /
b0000000000000000 0
b0000000000000000 1
b0000000000000000 2
b0000000000000000 3
b0000000000000000 4
b0000000000000000 5
b0000000000000000 6
b0000000000000000 7
b0000000000000000 8
b00000000000000000000000000000000 9
b0000000000000000 :
b00000000000000000000000000000000 ;
b0000000000000000 <
b00000000000000000000000000000000 =
b0000000000000000 >
b00000000000000000000000000000000 ?
b0000000000000000 @
b0000000000000000 A
b0000000000000000 B
b0000000000000000 C
b0000000000000000 D
b0000000000000000 E
b0000000000000000 F
b0000000000000000 G
b0000000000000000 H
b0000000000000000 I
0J
b00000000000000000000000000000000 K
b00000000000000000000000000000000 L
b00000000000000000000000000000000 M
b00000000000000000000000000000000 N
b00000000000000000000000000000000 O
b00000000000000000000000000000000 P
b00000000000000000000000000000000 Q
b00000000000000000000000000000000 R
b0000000000000000 S
b0000000000000000 T
b0000000000000000 U
b0000000000000000 V
b00000000000000000000000000000000 W
b00000000000000000000000000000000 X
b00000000000000000000000000000000 Y
b00000000000000000000000000000000 Z
b00000000000000000000000000000000 [
b00000000000000000000000000000000 \
0]
0^
0_
0`
b00000000000000000000000000000000 a
b00000000000000000000000000000000 b
b00000000000000000000000000000000 c
0d
b00000000000000000000000000000000 e
b00000000000000000000000000000000 f
b00000000000000000000000000000000 g
0h
b0000000000000000 i
0j
b0000000000000000 k
0l
b0000000000000000 m
0n
b0000000000000000 o
b00000000000000000000000000000000 p
b00000000000000000000000000000000 q
b00000000000000000000000000000000 r
b00000000000000000000000000000000 s
b00000000000000000000000000000000 t
b00000000000000000000000000000000 u
b00000000000000000000000000000000 v
b00000000000000000000000000000000 w
b00000000000000000000000000000000 x
b00000000000000000000000000000000 y
0z
b00000000000000000000000000000010 {
b00000000000000000000000000010000 |
b00000000000000000000000000100000 }
b00000000000000000000000000000100 ~
0!!
b00000000000000000000000000000000 "!
b00000000000000000000000000000010 #!
b0000000000000000 $!
b0000000000000000 %!
b0000000000000000 &!
b0000000000000000 '!
b00000000000000000000000000000000 (!
b00000000000000000000000000000000 )!
b00000000000000000000000000000000 *!
b0000000000000000 +!
b0000000000000000 ,!
b0000000000000000 -!
b0000000000000000 .!
b00000000000000000000000000000000 /!
b00000000000000000000000000000000 0!
b00000000000000000000000000000000 1!
b0000000000000000 2!
b0000000000000000 3!
b0000000000000000 4!
b0000000000000000 5!
b00000000000000000000000000000000 6!
b00000000000000000000000000000000 7!
b00000000000000000000000000000000 8!
b0000000000000000 9!
b0000000000000000 :!
b0000000000000000 ;!
b0000000000000000 <!
b00000000000000000000000000000000 =!
b00000000000000000000000000000000 >!
b00000000000000000000000000000000 ?!
#5
b00000000000000000000000000000010 a
b00000000000000000000000000000010 b
1z
#10
1$
b0000000000000001 &
b0000000000000010 '
b0000000000000011 (
b0000000000000100 )
b0000000000000101 *
b0000000000000110 +
b0000000000000111 ,
b0000000000001000 -
b0000000000000001 0
b0000000000000010 1
b0000000000000011 2
b0000000000000100 3
b0000000000000101 4
b0000000000000110 5
b0000000000000111 6
b0000000000001000 7
0z
#15
b0000000000000101 S
b0000000000000110 T
b0000000000000111 U
b0000000000001000 V
1d
b0000000000000101 i
b0000000000000110 k
b0000000000000111 m
b0000000000001000 o
1z
#20
0z
#25
0$
0%
b0000000000000001 @
b0000000000000010 C
b0000000000000001 F
b0000000000000010 H
1]
1_
b00000000000000000000000000000011 a
b00000000000000000000000000000001 c
1h
1l
1z
#30
0z
#35
b0000000000000001 8
b00000000000000000000000000000101 9
b0000000000000010 <
b00000000000000000000000000001110 =
b0000000000000011 @
b0000000000000001 A
b0000000000000100 C
b0000000000000010 D
b0000000000000011 F
b0000000000000001 G
b0000000000000100 H
b0000000000000010 I
1^
1`
b00000000000000000000000000000010 c
1j
1n
b00000000000000000000000000000101 r
b00000000000000000000000000001110 t
b00000000000000000000000000000101 v
b00000000000000000000000000001110 x
1z
#40
0z
#45
b0000000000000011 8
b00000000000000000000000000001111 9
b0000000000000001 :
b00000000000000000000000000000110 ;
b0000000000000100 <
b00000000000000000000000000011100 =
b0000000000000010 >
b00000000000000000000000000010000 ?
b0000000000000000 @
b0000000000000011 A
b0000000000000001 B
b0000000000000000 C
b0000000000000100 D
b0000000000000010 E
b0000000000000000 F
b0000000000000011 G
b0000000000000000 H
b0000000000000100 I
b00000000000000000000000000000101 Y
b00000000000000000000000000010011 [
b00000000000000000000000000000011 c
b00000000000000000000000000010011 e
b00000000000000000000000000001111 r
b00000000000000000000000000000110 s
b00000000000000000000000000011100 t
b00000000000000000000000000010000 u
b00000000000000000000000000001111 v
b00000000000000000000000000000110 w
b00000000000000000000000000011100 x
b00000000000000000000000000010000 y
1z
#50
0z
#55
b0000000000000000 8
b00000000000000000000000000000000 9
b0000000000000011 :
b00000000000000000000000000010010 ;
b0000000000000000 <
b00000000000000000000000000000000 =
b0000000000000100 >
b00000000000000000000000000100000 ?
b0000000000000000 A
b0000000000000011 B
b0000000000000000 D
b0000000000000100 E
b0000000000000000 G
b0000000000000000 I
b00000000000000000000000000010011 K
b00000000000000000000000000010011 O
b00000000000000000000000000001111 Y
b00000000000000000000000000000110 Z
b00000000000000000000000000101011 [
b00000000000000000000000000010110 \
0_
b00000000000000000000000000000100 c
b00000000000000000000000000101011 e
b00000000000000000000000000010110 f
b00000000000000000000000000000001 g
0l
b00000000000000000000000000000000 r
b00000000000000000000000000010010 s
b00000000000000000000000000000000 t
b00000000000000000000000000100000 u
b00000000000000000000000000000000 v
b00000000000000000000000000010010 w
b00000000000000000000000000000000 x
b00000000000000000000000000100000 y
1z
#60
0z
#65
b0000000000000000 :
b00000000000000000000000000000000 ;
b0000000000000000 >
b00000000000000000000000000000000 ?
b0000000000000000 B
b0000000000000000 E
b00000000000000000000000000010110 L
b00000000000000000000000000101011 M
b00000000000000000000000000010110 P
b00000000000000000000000000101011 Q
b00000000000000000000000000000000 Y
b00000000000000000000000000010010 Z
b00000000000000000000000000000000 [
b00000000000000000000000000110010 \
0]
0`
b00000000000000000000000000000101 c
b00000000000000000000000000000000 e
b00000000000000000000000000110010 f
b00000000000000000000000000000010 g
0h
0n
b00000000000000000000000000000000 s
b00000000000000000000000000000000 u
b00000000000000000000000000000000 w
b00000000000000000000000000000000 y
1z
#70
0z
#75
b00000000000000000000000000000010 .
b00000000000000000000000000000010 /
1J
b00000000000000000000000000110010 N
b00000000000000000000000000110010 R
b00000000000000000000000000000000 Z
b00000000000000000000000000000000 \
0^
b00000000000000000000000000000110 c
0d
b00000000000000000000000000000000 f
b00000000000000000000000000000011 g
0j
1z
#80
0z
#85
0J
1z
