MAC_unit.sv
`timescale 1ns / 1ns

module MAC_unit#(
    parameter A_Input_Width = 16,   // Width of input A and B
    parameter C_Output_Width = 32   // Width of output C (Accumulated result)
)(
    input logic clk,
    input logic reset,
    input logic enable,
    input logic signed [A_Input_Width-1:0] A_in,
    // input logic signed [A_Input_Width-1:0] A_in[N][N],
    // input logic signed [A_Input_Width-1:0] B_in[N][N],
    input logic signed [A_Input_Width-1:0] B_in,
    // input logic signed [C_Output_Width-1:0] C_in,
    output logic signed [A_Input_Width-1:0] A_out,
    output logic signed [A_Input_Width-1:0] B_out,
    output logic signed [C_Output_Width-1:0] C_out
);

logic signed [C_Output_Width-1:0] Acc_reg; //Internal reg

localparam Prod_Width = A_Input_Width*2; // Width after multiplication
logic signed [Prod_Width-1:0] Product;

assign Product = A_in * B_in; // Signed multiplication

always_ff @(posedge clk) begin
    if (reset)
    begin
    A_out <= 0;
        B_out <= 0;
        Acc_reg <= 0;
    end

    else begin
    if (enable) begin
        Acc_reg <= Acc_reg + $signed(Product);
        A_out <= A_in;
        B_out <= B_in;
    end
    else begin
        Acc_reg <= Acc_reg; 
        A_out <= A_out;
        B_out <= B_out;
    end

    
    end
end
assign C_out = Acc_reg;
endmodule

Systolic_Array.sv
module Systolic_Array #(
    parameter N=2,
    parameter A_Input_Width =16,
    parameter C_Output_Width =32)(
    input logic clk,
    input logic reset,
    input logic start,
    input logic enable,
    // input logic signed [N_Elements-1:0][A_Input_Width-1:0] A_in,
    input logic signed [A_Input_Width-1:0] A_in [N][N],
    // input logic signed [N_Elements-1:0][A_Input_Width-1:0] B_in,
    input logic signed [A_Input_Width-1:0] B_in [N][N],
    output logic signed [C_Output_Width-1:0] C_out[N][N],
    output logic done
    );

localparam N_Elements = N*N;
logic signed [A_Input_Width-1:0] A_bus[0:N-1][0:N]; // Extra column for input coming in from left
logic signed [A_Input_Width-1:0] B_bus[0:N][0:N-1]; // Extra row for input coming in from top
logic signed [C_Output_Width-1:0] C_bus[0:N-1][0:N-1]; // Accumulation matrix for each MAC unit
// logic signed [N_Elements-1:0][A_Input_Width-1:0] B_in_staggered = B_in;
logic signed [A_Input_Width-1:0] B_in_staggered[N][N];
assign B_in_staggered = B_in; // Direct assignment for now

logic enable_bus[0:N-1][0:N-1]; // Enable signals for clock-gating each MAC unit
integer i, j;
int row_i, col_j;   // Loop variable to track the current input element being processed
int clkcount; // Counter to track the number of clock cycles and the progress of computation
logic running; // Signal to indicate the start of computation



always_ff @(posedge clk or posedge reset) begin
    if (reset) begin
        clkcount <= '0; // Reset clock counter, running and done signals
        running <= 1'b0;
        done <= 1'b0;
        for (i = 0; i < N; i = i + 1) begin
            for (j = 0; j < N; j = j + 1) begin
                enable_bus[i][j] <= 1'b0;
                C_out[i][j] <= '0; // Initialize accumulation registers to zero
                A_bus[i][j] <= '0; // Initialize A and B buses to zero
                B_bus[i][j] <= '0;
            end
        end
    end

    else begin 
        done <= 1'b0;

        

        if (start&&!running) begin // Start signal received
            running <= 1'b1;
            clkcount <= '0; // Reset clock counter at the start of computation
        end
    

        else if (running) begin
            clkcount <= clkcount + 1;

            for (row_i =0; row_i<N; row_i = row_i +1) begin
                for (col_j =0; col_j<N; col_j = col_j +1) begin
                    if (clkcount >= row_i + col_j && clkcount < row_i + col_j + N) begin
                        enable_bus[row_i][col_j] <= 1'b1; // Enable MAC units along the wavefront diagonal
                    end
                    else begin
                        enable_bus[row_i][col_j] <= 1'b0;
                    end
                end
            end

            // Shift A and B values through the array
            for (row_i = 0; row_i < N; row_i = row_i + 1) begin // Shift A input values to the right
                if (clkcount >= row_i && clkcount < row_i + N) begin
                    A_bus[row_i][0] <= A_in[row_i][clkcount - row_i]; 
                end
                else begin
                    A_bus[row_i][0] <= '0; // Zero input after the cycle ends
                end
            end
            

            for (col_j = 0; col_j < N; col_j = col_j + 1) begin // Shift B input values down
                if (clkcount >= col_j && clkcount < col_j + N) begin
                    B_bus[0][col_j] <= B_in_staggered[clkcount - col_j][col_j]; 
                end
                else begin
                B_bus[0][col_j] <= '0; // Zero input after the cycle ends
                end
            end
            

            if (clkcount >= N*2) begin // Computation is complete after N*2 cycles
                running <= 1'b0;
                done <= 1'b1;
            end
        end
    end
end

        genvar r, c;
        generate

            for (r = 0; r < N; r = r + 1) begin : row_loop
                for (c = 0; c < N; c = c + 1) begin : col_loop
                    logic signed [A_Input_Width-1:0] A_in_wire, B_in_wire;
                    logic signed [A_Input_Width-1:0] A_out_wire, B_out_wire;
                    logic signed [C_Output_Width-1:0] C_out_wire;

                    // assign A_in_wire = A_bus[r][c]; // Connect A and B inputs from the bus
                    // assign B_in_wire = B_bus[r][c];

                    // assign enable_bus[r][c] = enable;   // Clock-gate each MAC unit based on the global enable signal

                    MAC_unit #(
                        .A_Input_Width(A_Input_Width),
                        .C_Output_Width(C_Output_Width)
                    )

                    mac_inst(
                        .clk(clk),
                        .reset(reset),
                        .enable(enable_bus[r][c]),
                        .A_in(A_bus[r][c]), // Connect A and B inputs from the bus
                        .B_in(B_bus[r][c]),
                        // .C_in(C_bus[r][c]),
                        .A_out(A_bus[r][c+1]), // Forward A output to the right
                        .B_out(B_bus[r+1][c]), // Forward B output downwards
                        .C_out(C_out[r][c])
                    );

                end
            end
        endgenerate


endmodule

tb_systolicarray_2x2.sv
`timescale 1ns/1ns

module tb_systolicarray_2x2;

localparam N = 2;
localparam A_Input_Width = 16;
localparam C_Output_Width = 32;
localparam N_Elements = N*N;

logic clk;
logic reset;
logic enable;
logic start;
wire done;
// logic [N_Elements-1:0][A_Input_Width-1:0] A_in;  
logic [A_Input_Width-1:0] A_in [N][N];
// logic [N_Elements-1:0][A_Input_Width-1:0] B_in;  
logic [A_Input_Width-1:0] B_in [N][N];
wire [C_Output_Width-1:0] C_out[N][N];

    // Instantiate DUT
    Systolic_Array dut (
        .clk(clk),
        .reset(reset),
        .enable(enable),
        .A_in(A_in),
        .B_in(B_in),
        .C_out(C_out),
        .start(start),
        .done(done)

    );

    // Clock generation
    always #5 clk = ~clk; // 10ns period, 100MHz

    integer i, j;

    initial begin
        $display("---- Systolic Array 2x2 Testbench Start ----");
        
        $dumpfile("tb_systolicarray_2x2.vcd");
        $dumpvars(0, tb_systolicarray_2x2);
        clk = 0;
        reset = 0;
        #10;
        start = 1;
        enable = 1;

        // Example matrices:
        // A = [1 2; 3 4]
        // B = [5 6; 7 8]
        A_in[0][0] = 'd1; A_in[0][1] = 'd2;
        A_in[1][0] = 'd3; A_in[1][1] = 'd4;
        // A_in[0] = 'd1; A_in[1] = 'd2;
        // A_in[2] = 'd3; A_in[3] = 'd4;
        // B_in = '{
        // '{16'd5, 16'd6},     // row 0
        // '{16'd7, 16'd8}      // row 1
        // };
        B_in[0][0] = 'd5; B_in[0][1] = 'd6;      //why isn't this working??!!
        B_in[1][0] = 'd7;                        // weird...it works after commenting above assignments
        B_in[1][1] = 'd8;
        // B_in[0] = 'd5; B_in[1] = 'd6;
        // B_in[2] = 'd7; B_in[3] = 'd8;
        // Reset pulse
        // #5;
        // reset = 0;

        //  enable = 1;
        // @(posedge clk);
        // start = 1;
        #10;
        @(posedge clk);
        start = 0;

        // Wait enough cycles for systolic pipeline
        //  #150;
        $display("reset= %d, start= %d, done= %d, running= %d, clkcount= %d", reset, start, done, dut.running, dut.clkcount);
        wait (done == 1);

        $display("Computed Matrix C:");
        for (i = 0; i < 2; i = i + 1) begin
            for (j = 0; j < 2; j = j + 1) begin
                $display("C[%0d][%0d] = %0d", i, j, C_out[i][j]);
            end
        end

        // Expected result:
        // [1*5 + 2*7, 1*6 + 2*8] = [19, 22]
        // [3*5 + 4*7, 3*6 + 4*8] = [43, 50]

        $display("Expected:");
        $display("C = [19 22; 43 50]");
        #10;

        $display("---- Test Completed ----");
        $finish;
    end

endmodule

obj_dir/tb_systolicarray_2x2.vcd
$version Generated by VerilatedVcd $end
$timescale 1ns $end
 $scope module tb_systolicarray_2x2 $end
  $var wire 32 x N [31:0] $end
  $var wire 32 y A_Input_Width [31:0] $end
  $var wire 32 z C_Output_Width [31:0] $end
  $var wire 32 { N_Elements [31:0] $end
  $var wire 1 w clk $end
  $var wire 1 # reset $end
  $var wire 1 $ enable $end
  $var wire 1 % start $end
  $var wire 1 < done $end
  $var wire 16 & A_in[0][0] [15:0] $end
  $var wire 16 ' A_in[0][1] [15:0] $end
  $var wire 16 ( A_in[1][0] [15:0] $end
  $var wire 16 ) A_in[1][1] [15:0] $end
  $var wire 16 * B_in[0][0] [15:0] $end
  $var wire 16 + B_in[0][1] [15:0] $end
  $var wire 16 , B_in[1][0] [15:0] $end
  $var wire 16 - B_in[1][1] [15:0] $end
  $var wire 32 o C_out[0][0] [31:0] $end
  $var wire 32 p C_out[0][1] [31:0] $end
  $var wire 32 q C_out[1][0] [31:0] $end
  $var wire 32 r C_out[1][1] [31:0] $end
  $var wire 32 . i [31:0] $end
  $var wire 32 / j [31:0] $end
  $scope module dut $end
   $var wire 32 x N [31:0] $end
   $var wire 32 y A_Input_Width [31:0] $end
   $var wire 32 z C_Output_Width [31:0] $end
   $var wire 1 w clk $end
   $var wire 1 # reset $end
   $var wire 1 % start $end
   $var wire 1 $ enable $end
   $var wire 16 0 A_in[0][0] [15:0] $end
   $var wire 16 1 A_in[0][1] [15:0] $end
   $var wire 16 2 A_in[1][0] [15:0] $end
   $var wire 16 3 A_in[1][1] [15:0] $end
   $var wire 16 4 B_in[0][0] [15:0] $end
   $var wire 16 5 B_in[0][1] [15:0] $end
   $var wire 16 6 B_in[1][0] [15:0] $end
   $var wire 16 7 B_in[1][1] [15:0] $end
   $var wire 32 s C_out[0][0] [31:0] $end
   $var wire 32 t C_out[0][1] [31:0] $end
   $var wire 32 u C_out[1][0] [31:0] $end
   $var wire 32 v C_out[1][1] [31:0] $end
   $var wire 1 < done $end
   $var wire 32 { N_Elements [31:0] $end
   $var wire 16 O A_bus[0][0] [15:0] $end
   $var wire 16 P A_bus[0][1] [15:0] $end
   $var wire 16 Q A_bus[0][2] [15:0] $end
   $var wire 16 R A_bus[1][0] [15:0] $end
   $var wire 16 S A_bus[1][1] [15:0] $end
   $var wire 16 T A_bus[1][2] [15:0] $end
   $var wire 16 U B_bus[0][0] [15:0] $end
   $var wire 16 V B_bus[0][1] [15:0] $end
   $var wire 16 W B_bus[1][0] [15:0] $end
   $var wire 16 X B_bus[1][1] [15:0] $end
   $var wire 16 Y B_bus[2][0] [15:0] $end
   $var wire 16 Z B_bus[2][1] [15:0] $end
   $var wire 32 | C_bus[0][0] [31:0] $end
   $var wire 32 } C_bus[0][1] [31:0] $end
   $var wire 32 ~ C_bus[1][0] [31:0] $end
   $var wire 32 !! C_bus[1][1] [31:0] $end
   $var wire 16 8 B_in_staggered[0][0] [15:0] $end
   $var wire 16 9 B_in_staggered[0][1] [15:0] $end
   $var wire 16 : B_in_staggered[1][0] [15:0] $end
   $var wire 16 ; B_in_staggered[1][1] [15:0] $end
   $var wire 1 g enable_bus[0][0] $end
   $var wire 1 h enable_bus[0][1] $end
   $var wire 1 i enable_bus[1][0] $end
   $var wire 1 j enable_bus[1][1] $end
   $var wire 32 = i [31:0] $end
   $var wire 32 > j [31:0] $end
   $var wire 32 ? row_i [31:0] $end
   $var wire 32 @ col_j [31:0] $end
   $var wire 32 A clkcount [31:0] $end
   $var wire 1 B running $end
   $scope module row_loop[0] $end
    $scope module col_loop[0] $end
     $var wire 16 "! A_in_wire [15:0] $end
     $var wire 16 #! B_in_wire [15:0] $end
     $var wire 16 $! A_out_wire [15:0] $end
     $var wire 16 %! B_out_wire [15:0] $end
     $var wire 32 &! C_out_wire [31:0] $end
     $scope module mac_inst $end
      $var wire 32 y A_Input_Width [31:0] $end
      $var wire 32 z C_Output_Width [31:0] $end
      $var wire 1 w clk $end
      $var wire 1 # reset $end
      $var wire 1 k enable $end
      $var wire 16 [ A_in [15:0] $end
      $var wire 16 \ B_in [15:0] $end
      $var wire 16 C A_out [15:0] $end
      $var wire 16 D B_out [15:0] $end
      $var wire 32 E C_out [31:0] $end
      $var wire 32 E Acc_reg [31:0] $end
      $var wire 32 z Prod_Width [31:0] $end
      $var wire 32 ] Product [31:0] $end
     $upscope $end
    $upscope $end
    $scope module col_loop[1] $end
     $var wire 16 '! A_in_wire [15:0] $end
     $var wire 16 (! B_in_wire [15:0] $end
     $var wire 16 )! A_out_wire [15:0] $end
     $var wire 16 *! B_out_wire [15:0] $end
     $var wire 32 +! C_out_wire [31:0] $end
     $scope module mac_inst $end
      $var wire 32 y A_Input_Width [31:0] $end
      $var wire 32 z C_Output_Width [31:0] $end
      $var wire 1 w clk $end
      $var wire 1 # reset $end
      $var wire 1 l enable $end
      $var wire 16 ^ A_in [15:0] $end
      $var wire 16 _ B_in [15:0] $end
      $var wire 16 F A_out [15:0] $end
      $var wire 16 G B_out [15:0] $end
      $var wire 32 H C_out [31:0] $end
      $var wire 32 H Acc_reg [31:0] $end
      $var wire 32 z Prod_Width [31:0] $end
      $var wire 32 ` Product [31:0] $end
     $upscope $end
    $upscope $end
   $upscope $end
   $scope module row_loop[1] $end
    $scope module col_loop[0] $end
     $var wire 16 ,! A_in_wire [15:0] $end
     $var wire 16 -! B_in_wire [15:0] $end
     $var wire 16 .! A_out_wire [15:0] $end
     $var wire 16 /! B_out_wire [15:0] $end
     $var wire 32 0! C_out_wire [31:0] $end
     $scope module mac_inst $end
      $var wire 32 y A_Input_Width [31:0] $end
      $var wire 32 z C_Output_Width [31:0] $end
      $var wire 1 w clk $end
      $var wire 1 # reset $end
      $var wire 1 m enable $end
      $var wire 16 a A_in [15:0] $end
      $var wire 16 b B_in [15:0] $end
      $var wire 16 I A_out [15:0] $end
      $var wire 16 J B_out [15:0] $end
      $var wire 32 K C_out [31:0] $end
      $var wire 32 K Acc_reg [31:0] $end
      $var wire 32 z Prod_Width [31:0] $end
      $var wire 32 c Product [31:0] $end
     $upscope $end
    $upscope $end
    $scope module col_loop[1] $end
     $var wire 16 1! A_in_wire [15:0] $end
     $var wire 16 2! B_in_wire [15:0] $end
     $var wire 16 3! A_out_wire [15:0] $end
     $var wire 16 4! B_out_wire [15:0] $end
     $var wire 32 5! C_out_wire [31:0] $end
     $scope module mac_inst $end
      $var wire 32 y A_Input_Width [31:0] $end
      $var wire 32 z C_Output_Width [31:0] $end
      $var wire 1 w clk $end
      $var wire 1 # reset $end
      $var wire 1 n enable $end
      $var wire 16 d A_in [15:0] $end
      $var wire 16 e B_in [15:0] $end
      $var wire 16 L A_out [15:0] $end
      $var wire 16 M B_out [15:0] $end
      $var wire 32 N C_out [31:0] $end
      $var wire 32 N Acc_reg [31:0] $end
      $var wire 32 z Prod_Width [31:0] $end
      $var wire 32 f Product [31:0] $end
     $upscope $end
    $upscope $end
   $upscope $end
  $upscope $end
 $upscope $end
$enddefinitions $end


#0
0#
0$
0%
b0000000000000000 &
b0000000000000000 '
b0000000000000000 (
b0000000000000000 )
b0000000000000000 *
b0000000000000000 +
b0000000000000000 ,
b0000000000000000 -
b00000000000000000000000000000000 .
b00000000000000000000000000000000 /
b0000000000000000 0
b0000000000000000 1
b0000000000000000 2
b0000000000000000 3
b0000000000000000 4
b0000000000000000 5
b0000000000000000 6
b0000000000000000 7
b0000000000000000 8
b0000000000000000 9
b0000000000000000 :
b0000000000000000 ;
0<
b00000000000000000000000000000000 =
b00000000000000000000000000000000 >
b00000000000000000000000000000000 ?
b00000000000000000000000000000000 @
b00000000000000000000000000000000 A
0B
b0000000000000000 C
b0000000000000000 D
b00000000000000000000000000000000 E
b0000000000000000 F
b0000000000000000 G
b00000000000000000000000000000000 H
b0000000000000000 I
b0000000000000000 J
b00000000000000000000000000000000 K
b0000000000000000 L
b0000000000000000 M
b00000000000000000000000000000000 N
b0000000000000000 O
b0000000000000000 P
b0000000000000000 Q
b0000000000000000 R
b0000000000000000 S
b0000000000000000 T
b0000000000000000 U
b0000000000000000 V
b0000000000000000 W
b0000000000000000 X
b0000000000000000 Y
b0000000000000000 Z
b0000000000000000 [
b0000000000000000 \
b00000000000000000000000000000000 ]
b0000000000000000 ^
b0000000000000000 _
b00000000000000000000000000000000 `
b0000000000000000 a
b0000000000000000 b
b00000000000000000000000000000000 c
b0000000000000000 d
b0000000000000000 e
b00000000000000000000000000000000 f
0g
0h
0i
0j
0k
0l
0m
0n
b00000000000000000000000000000000 o
b00000000000000000000000000000000 p
b00000000000000000000000000000000 q
b00000000000000000000000000000000 r
b00000000000000000000000000000000 s
b00000000000000000000000000000000 t
b00000000000000000000000000000000 u
b00000000000000000000000000000000 v
0w
b00000000000000000000000000000010 x
b00000000000000000000000000010000 y
b00000000000000000000000000100000 z
b00000000000000000000000000000100 {
b00000000000000000000000000000000 |
b00000000000000000000000000000000 }
b00000000000000000000000000000000 ~
b00000000000000000000000000000000 !!
b0000000000000000 "!
b0000000000000000 #!
b0000000000000000 $!
b0000000000000000 %!
b00000000000000000000000000000000 &!
b0000000000000000 '!
b0000000000000000 (!
b0000000000000000 )!
b0000000000000000 *!
b00000000000000000000000000000000 +!
b0000000000000000 ,!
b0000000000000000 -!
b0000000000000000 .!
b0000000000000000 /!
b00000000000000000000000000000000 0!
b0000000000000000 1!
b0000000000000000 2!
b0000000000000000 3!
b0000000000000000 4!
b00000000000000000000000000000000 5!
#5
1w
#10
1$
1%
b0000000000000001 &
b0000000000000010 '
b0000000000000011 (
b0000000000000100 )
b0000000000000101 *
b0000000000000110 +
b0000000000000111 ,
b0000000000001000 -
b0000000000000001 0
b0000000000000010 1
b0000000000000011 2
b0000000000000100 3
b0000000000000101 4
b0000000000000110 5
b0000000000000111 6
b0000000000001000 7
b0000000000000101 8
b0000000000000110 9
b0000000000000111 :
b0000000000001000 ;
0w
#15
1B
1w
#20
0w
#25
0%
b00000000000000000000000000000010 ?
b00000000000000000000000000000010 @
b00000000000000000000000000000001 A
b0000000000000001 O
b0000000000000101 U
b0000000000000001 [
b0000000000000101 \
b00000000000000000000000000000101 ]
1g
1k
1w
#30
0w
#35
b00000000000000000000000000000010 A
b0000000000000001 C
b0000000000000101 D
b00000000000000000000000000000101 E
b0000000000000010 O
b0000000000000001 P
b0000000000000011 R
b0000000000000111 U
b0000000000000110 V
b0000000000000101 W
b0000000000000010 [
b0000000000000111 \
b00000000000000000000000000001110 ]
b0000000000000001 ^
b0000000000000110 _
b00000000000000000000000000000110 `
b0000000000000011 a
b0000000000000101 b
b00000000000000000000000000001111 c
1h
1i
1l
1m
b00000000000000000000000000000101 o
b00000000000000000000000000000101 s
1w
#40
0w
#45
b00000000000000000000000000000011 A
b0000000000000010 C
b0000000000000111 D
b00000000000000000000000000010011 E
b0000000000000001 F
b0000000000000110 G
b00000000000000000000000000000110 H
b0000000000000011 I
b0000000000000101 J
b00000000000000000000000000001111 K
b0000000000000000 O
b0000000000000010 P
b0000000000000001 Q
b0000000000000100 R
b0000000000000011 S
b0000000000000000 U
b0000000000001000 V
b0000000000000111 W
b0000000000000110 X
b0000000000000101 Y
b0000000000000000 [
b0000000000000000 \
b00000000000000000000000000000000 ]
b0000000000000010 ^
b0000000000001000 _
b00000000000000000000000000010000 `
b0000000000000100 a
b0000000000000111 b
b00000000000000000000000000011100 c
b0000000000000011 d
b0000000000000110 e
b00000000000000000000000000010010 f
0g
1j
0k
1n
b00000000000000000000000000010011 o
b00000000000000000000000000000110 p
b00000000000000000000000000001111 q
b00000000000000000000000000010011 s
b00000000000000000000000000000110 t
b00000000000000000000000000001111 u
1w
#50
0w
#55
b00000000000000000000000000000100 A
b0000000000000010 F
b0000000000001000 G
b00000000000000000000000000010110 H
b0000000000000100 I
b0000000000000111 J
b00000000000000000000000000101011 K
b0000000000000011 L
b0000000000000110 M
b00000000000000000000000000010010 N
b0000000000000010 Q
b0000000000000000 R
b0000000000000100 S
b0000000000000011 T
b0000000000000000 V
b0000000000001000 X
b0000000000000111 Y
b0000000000000110 Z
b0000000000000000 _
b00000000000000000000000000000000 `
b0000000000000000 a
b00000000000000000000000000000000 c
b0000000000000100 d
b0000000000001000 e
b00000000000000000000000000100000 f
0h
0i
0l
0m
b00000000000000000000000000010110 p
b00000000000000000000000000101011 q
b00000000000000000000000000010010 r
b00000000000000000000000000010110 t
b00000000000000000000000000101011 u
b00000000000000000000000000010010 v
1w
#60
0w
#65
b00000000000000000000000000000010 .
b00000000000000000000000000000010 /
1<
b00000000000000000000000000000101 A
0B
b0000000000000100 L
b0000000000001000 M
b00000000000000000000000000110010 N
b0000000000000100 T
b0000000000001000 Z
0j
0n
b00000000000000000000000000110010 r
b00000000000000000000000000110010 v
1w
#70
0w
#75
0<
1w
